Thejairex/__init__.py
Thejairex/agent.py
Thejairex/proxy.py
Thejairex-0.1.2.dist-info/LICENSE
Thejairex-0.1.2.dist-info/METADATA
Thejairex-0.1.2.dist-info/WHEEL
Thejairex-0.1.2.dist-info/top_level.txt
Thejairex-0.1.2.dist-info/RECORD
